{
    "type": "filament",
    "name": "Orca Arena Arena PC @BBL X1 0.2 nozzle",
    "inherits": "Orca Arena Arena PC @base",
    "from": "system",
    "setting_id": "GFS106_02",
    "instantiation": "true",
    "eng_plate_temp": [
        "100"
    ],
    "eng_plate_temp_initial_layer": [
        "100"
    ],
    "hot_plate_temp": [
        "110.0"
    ],
    "hot_plate_temp_initial_layer": [
        "110.0"
    ],
    "textured_plate_temp": [
        "110.0"
    ],
    "textured_plate_temp_initial_layer": [
        "100"
    ],
    "compatible_printers": [
        "Bambu Lab X1 0.2 nozzle"
    ]
}
