{
    "type": "filament",
    "name": "Ultimaker PC @base",
    "inherits": "fdm_filament_pc",
    "from": "system",
    "filament_id": "GFM04",
    "instantiation": "false",
    "filament_vendor": [
        "Ultimaker"
    ],
    "filament_cost": [
        "39.99"
    ],
    "filament_flow_ratio": [
        "0.94"
    ],
    "filament_density": [
        "1.19"
    ],
    "impact_strength_z": [
        "9.0"
    ],
    "cool_plate_temp": [
        "0"
    ],
    "cool_plate_temp_initial_layer": [
        "0"
    ],
    "eng_plate_temp": [
        "107"
    ],
    "eng_plate_temp_initial_layer": [
        "107"
    ],
    "hot_plate_temp": [
        "107"
    ],
    "hot_plate_temp_initial_layer": [
        "107"
    ],
    "textured_plate_temp": [
        "107"
    ],
    "textured_plate_temp_initial_layer": [
        "107"
    ],
    "supertack_plate_temp": [
        "0"
    ],
    "supertack_plate_temp_initial_layer": [
        "0"
    ],
    "chamber_temperatures": [
        "50"
    ]
}
